loglense-0.1.0.dist-info/licenses/LICENSE
loglense_package/__init__.py
loglense_package/main.py
loglense_package/providers.py
loglense_package/test_logs/generate_large_logs.py
loglense-0.1.0.dist-info/METADATA
loglense-0.1.0.dist-info/WHEEL
loglense-0.1.0.dist-info/entry_points.txt
loglense-0.1.0.dist-info/top_level.txt
loglense-0.1.0.dist-info/RECORD
